rtmilk/__init__.py
rtmilk/_properties.py
rtmilk/_sansio.py
rtmilk/_secrets.py
rtmilk/_utils.py
rtmilk/api_async.py
rtmilk/api_base.py
rtmilk/api_sync.py
rtmilk/authorization.py
rtmilk/client.py
rtmilk/filter.py
rtmilk/mirror.py
rtmilk/models.py
rtmilk/py.typed
rtmilk-3.0.5.dist-info/METADATA
rtmilk-3.0.5.dist-info/WHEEL
rtmilk-3.0.5.dist-info/licenses/LICENSE
rtmilk-3.0.5.dist-info/RECORD
