Metadata-Version: 2.4
Name: rtmilk
Version: 3.0.5
Summary: Remember The Milk API wrapper
Project-URL: Homepage, https://github.com/rkhwaja/rtmilk
Maintainer-email: Rehan Khwaja <rehan@khwaja.name>
License-Expression: MIT
License-File: LICENSE
Keywords: Milk,Remember,RememberTheMilk
Classifier: Development Status :: 5 - Production/Stable
Classifier: Intended Audience :: Developers
Classifier: Programming Language :: Python :: 3.10
Classifier: Programming Language :: Python :: 3.11
Classifier: Programming Language :: Python :: 3.12
Classifier: Programming Language :: Python :: 3.13
Classifier: Programming Language :: Python :: 3.14
Requires-Python: >=3.10
Requires-Dist: aiohttp>=3.9
Requires-Dist: listdiff>=1.0.2
Requires-Dist: pydantic>=2.8
Requires-Dist: requests>=2.23.0
Requires-Dist: urllib3>=1.26; python_version >= '3.10'
